election_results_xml_validator/__init__.py
election_results_xml_validator/base.py
election_results_xml_validator/rules.py
election_results_xml_validator-0.2.9.5.dist-info/LICENSE-2.0.txt
election_results_xml_validator-0.2.9.5.dist-info/METADATA
election_results_xml_validator-0.2.9.5.dist-info/WHEEL
election_results_xml_validator-0.2.9.5.dist-info/entry_points.txt
election_results_xml_validator-0.2.9.5.dist-info/top_level.txt
election_results_xml_validator-0.2.9.5.dist-info/RECORD
