Metadata-Version: 2.1
Name: election-results-xml-validator
Version: 0.2.9.5
Summary: Checks if an election feed follows best practices
Home-page: https://github.com/google/election_results_xml_validator
Author: Google Civics
Author-email: election-results-xml-validator@google.com
Maintainer: gVelocity Civics
Maintainer-email: election-results-xml-validator@google.com
License: Apache License
Platform: UNKNOWN
Requires-Dist: lxml (>=3.3.4)
Requires-Dist: language-tags (>=0.4.2)
Requires-Dist: requests (>=2.10)
Requires-Dist: pygithub (>=1.28)
